{
  "status": "success",
  "source": "semantic_scholar",
  "query": "Edward Shils tradition social theory",
  "results": [
    {
      "paperId": "1f990547d7ff5c37b6714a55d65ff0105f8b9bc5",
      "title": "Edward Shils' Theory of Tradition",
      "authors": [
        {
          "name": "Struan Jacobs",
          "authorId": "39340327"
        }
      ],
      "year": 2007,
      "abstract": null,
      "citationCount": 19,
      "doi": "10.1177/0048393107299685",
      "arxivId": null,
      "url": "https://www.semanticscholar.org/paper/1f990547d7ff5c37b6714a55d65ff0105f8b9bc5",
      "venue": "",
      "journal": {
        "name": "Philosophy of the Social Sciences",
        "pages": "139 - 162",
        "volume": "37"
      },
      "publicationTypes": [
        "JournalArticle"
      ]
    },
    {
      "paperId": "3639d1b9e200e748574d8fa06d06741c12399eae",
      "title": "Tradition . By Shils Edward. (Chicago: University of Chicago Press, 1981. Pp. viii + 334. $20.00.)",
      "authors": [
        {
          "name": "M. Oromaner",
          "authorId": "2024907"
        }
      ],
      "year": 1983,
      "abstract": null,
      "citationCount": 0,
      "doi": "10.2307/1957688",
      "arxivId": null,
      "url": "https://www.semanticscholar.org/paper/3639d1b9e200e748574d8fa06d06741c12399eae",
      "venue": "American Political Science Review",
      "journal": {
        "name": "American Political Science Review",
        "pages": "1124 - 1125",
        "volume": "77"
      },
      "publicationTypes": null
    },
    {
      "paperId": "982070484eeb57c9eea867ad79ba15ec6c797305",
      "title": "The virtue of civility : selected essays on liberalism, tradition, and civil society",
      "authors": [
        {
          "name": "E. Shils",
          "authorId": "32867104"
        },
        {
          "name": "Steven E. Grosby",
          "authorId": "102366437"
        }
      ],
      "year": 1997,
      "abstract": null,
      "citationCount": 104,
      "doi": null,
      "arxivId": null,
      "url": "https://www.semanticscholar.org/paper/982070484eeb57c9eea867ad79ba15ec6c797305",
      "venue": "",
      "journal": {
        "name": "",
        "volume": ""
      },
      "publicationTypes": null
    },
    {
      "paperId": "9c290da7400fe97c23bd7bac411db58f3c41d23e",
      "title": "Brains/Practices/Relativism: Social Theory after Cognitive Science",
      "authors": [
        {
          "name": "S. Turner",
          "authorId": "47505199"
        }
      ],
      "year": 2002,
      "abstract": null,
      "citationCount": 63,
      "doi": null,
      "arxivId": null,
      "url": "https://www.semanticscholar.org/paper/9c290da7400fe97c23bd7bac411db58f3c41d23e",
      "venue": "",
      "journal": {
        "name": "",
        "volume": ""
      },
      "publicationTypes": null
    },
    {
      "paperId": "dc6b1d8ba43aeaef90d6fa6b93c20a0c3bf06339",
      "title": "Tradition, genuine or spurious.",
      "authors": [
        {
          "name": "R. Handler",
          "authorId": "81191638"
        },
        {
          "name": "J. Linnekin",
          "authorId": "103988292"
        }
      ],
      "year": 1984,
      "abstract": null,
      "citationCount": 671,
      "doi": "10.2307/540610",
      "arxivId": null,
      "url": "https://www.semanticscholar.org/paper/dc6b1d8ba43aeaef90d6fa6b93c20a0c3bf06339",
      "venue": "",
      "journal": {
        "name": "Journal of American Folklore",
        "pages": "273-290",
        "volume": "97"
      },
      "publicationTypes": null
    },
    {
      "paperId": "f22dd039d31f3caa552b9c4a3b0c892fb782b96b",
      "title": "The Significance of Shils*",
      "authors": [
        {
          "name": "S. Turner",
          "authorId": "47505199"
        }
      ],
      "year": 1999,
      "abstract": null,
      "citationCount": 17,
      "doi": "10.1111/0735-2751.00072",
      "arxivId": null,
      "url": "https://www.semanticscholar.org/paper/f22dd039d31f3caa552b9c4a3b0c892fb782b96b",
      "venue": "",
      "journal": {
        "name": "Sociological Theory",
        "pages": "125 - 145",
        "volume": "17"
      },
      "publicationTypes": [
        "JournalArticle"
      ]
    },
    {
      "paperId": "9d17cd9cb3090e9468452d3547abc13cbf83ab09",
      "title": "The liberal Hegelianism of Edward Caird: Or, how to transcend the social economics of Kant and the romantics",
      "authors": [
        {
          "name": "C. Tyler",
          "authorId": "46825859"
        }
      ],
      "year": 2010,
      "abstract": null,
      "citationCount": 1,
      "doi": "10.1108/03068291011082829",
      "arxivId": null,
      "url": "https://www.semanticscholar.org/paper/9d17cd9cb3090e9468452d3547abc13cbf83ab09",
      "venue": "",
      "journal": {
        "name": "International Journal of Social Economics",
        "pages": "852-866",
        "volume": "37"
      },
      "publicationTypes": null
    },
    {
      "paperId": "8485577f8a27fa3264fb9a5a70d00cf9e50bc180",
      "title": "Business Ethics at the Millennium",
      "authors": [
        {
          "name": "R. Freeman",
          "authorId": "123851377"
        }
      ],
      "year": 2000,
      "abstract": null,
      "citationCount": 153,
      "doi": "10.2307/3857703",
      "arxivId": null,
      "url": "https://www.semanticscholar.org/paper/8485577f8a27fa3264fb9a5a70d00cf9e50bc180",
      "venue": "Business Ethics Quarterly",
      "journal": {
        "name": "Business Ethics Quarterly",
        "pages": "169 - 180",
        "volume": "10"
      },
      "publicationTypes": null
    },
    {
      "paperId": "222ff14bc7928c32f07a49b2514bbf992471a62c",
      "title": "Conceiving of tradition",
      "authors": [
        {
          "name": "Struan Jacobs",
          "authorId": "39340327"
        }
      ],
      "year": 2003,
      "abstract": null,
      "citationCount": 0,
      "doi": null,
      "arxivId": null,
      "url": "https://www.semanticscholar.org/paper/222ff14bc7928c32f07a49b2514bbf992471a62c",
      "venue": "",
      "journal": {
        "name": "",
        "pages": "1-7",
        "volume": ""
      },
      "publicationTypes": null
    },
    {
      "paperId": "f2bc9479870c992a31588d2429726d5578bd2145",
      "title": "Reflections on Shils, Sacred and Civil Ties, and Universities",
      "authors": [
        {
          "name": "Louis H. Swartz",
          "authorId": "153784599"
        }
      ],
      "year": 2000,
      "abstract": "This review essay, concerning three collections of Shils' essays published in 1997, focuses on Shils' assertion of the importance of charisma or the sacred in the ties that bind a secular society together and enable it to function as it does, asks why Shils did not accept Polanyi's views about intellectuals, and refers to aspects of the sacred attributed to universities and to our academic traditions. I Knowing of my interest in the relationship between Polanyi and Shils (e.g., Swartz 1998), Phil Mullins suggested that I write this short piece pertaining to three fairly recently published collections of Edward Shils' essays (Shils 1997a, 1997b, 1997c). Readers of TAD may be assumed to be aware of Turner's obituary of Shils, and of the posthumous publication of Shils' talk at Kent State concerning Polanyi on intellectuals (Shils 1995-96; Turner 1995-96). Both are worth rereading. One of my intentions in this essay is to pique and provoke further interest in Shils' writing. A second is to flag some questions about limitations of the influence of Polanyi on Shils, that bear further study. A third is to point to evidences of a contribution by Shils to sociological thought which I believe will be his most lastingly fruitful one, namely, his development of the idea of the power and importance of experiences and perceptions of the sacred in holding secular societies together and making them work as they do. II Not only does a current literature search show that Shils is still abundantly cited with respect to an amazing array of topics; he figures again in a current novel by Bellow (Staples 2000), and controversy continues concerning CIA funding of the Congress for Cultural Freedom in which both Shils and Polanyi played a part has recently published a thoughtful piece on certain aspects of Shils' contributions to social and political theory. In addition to the Shils' essays contained in these volumes, I enthusiastically commend to your attention the informative, reflective introduction to \" The Virtue of Civility \" (Shils 1997c) on the antinomies of liberalism, and on consensus and collective consciousness, by Professor Grosby, and on \" Edward Shils and the American University \" (Shils 1997b) by Professor Altbach, as well as the shorter introduction to \" The Calling of Education \" (Shils 1997a), again by Professor Grosby. I have not undertaken to cover the same ground that they have most ably chosen to deal \u2026",
      "citationCount": 1,
      "doi": "10.5840/TRADDISC2000/20012716",
      "arxivId": null,
      "url": "https://www.semanticscholar.org/paper/f2bc9479870c992a31588d2429726d5578bd2145",
      "venue": "",
      "journal": {
        "name": "",
        "pages": "7-12",
        "volume": "27"
      },
      "publicationTypes": [
        "Review"
      ]
    },
    {
      "paperId": "a08ccbf5ba7e183264cb86c8fd2d867d159af393",
      "title": "T.S. Eliot and the Concept of Tradition (review)",
      "authors": [
        {
          "name": "E. Lobb",
          "authorId": "118713054"
        }
      ],
      "year": 2010,
      "abstract": null,
      "citationCount": 0,
      "doi": null,
      "arxivId": null,
      "url": "https://www.semanticscholar.org/paper/a08ccbf5ba7e183264cb86c8fd2d867d159af393",
      "venue": "",
      "journal": {
        "name": "ESC: English Studies in Canada",
        "pages": "230 - 233",
        "volume": "35"
      },
      "publicationTypes": [
        "Review"
      ]
    },
    {
      "paperId": "96e7553a28c8b786b945c0f8a02d1785ff6f9520",
      "title": "Literary Theory: An Anthology",
      "authors": [
        {
          "name": "Julie Rivkin",
          "authorId": "113738269"
        },
        {
          "name": "Michael Ryan",
          "authorId": "47376427"
        }
      ],
      "year": 1998,
      "abstract": null,
      "citationCount": 474,
      "doi": "10.5860/choice.35-5478",
      "arxivId": null,
      "url": "https://www.semanticscholar.org/paper/96e7553a28c8b786b945c0f8a02d1785ff6f9520",
      "venue": "",
      "journal": {
        "name": "",
        "volume": ""
      },
      "publicationTypes": null
    },
    {
      "paperId": "f0e58ad7e8aee5d9767500b38c571c06297ff95b",
      "title": "Gestures of Despair and Hope: A View on Deliberate Self-harm From Economics and Evolutionary Biology",
      "authors": [
        {
          "name": "E. Hagen",
          "authorId": "2033615"
        },
        {
          "name": "P. Watson",
          "authorId": "2053066309"
        },
        {
          "name": "P. Hammerstein",
          "authorId": "2399129"
        }
      ],
      "year": 2008,
      "abstract": null,
      "citationCount": 39,
      "doi": "10.1162/BIOT.2008.3.2.123",
      "arxivId": null,
      "url": "https://www.semanticscholar.org/paper/f0e58ad7e8aee5d9767500b38c571c06297ff95b",
      "venue": "",
      "journal": {
        "name": "Biological Theory",
        "pages": "123-138",
        "volume": "3"
      },
      "publicationTypes": null
    },
    {
      "paperId": "baf3d092bb968f2350487b6afc673f38d354f793",
      "title": "Theory of Objective Mind: An Introduction to the Philosophy of Culture",
      "authors": [
        {
          "name": "H. Freyer",
          "authorId": "145735067"
        }
      ],
      "year": 1999,
      "abstract": null,
      "citationCount": 9,
      "doi": "10.2307/3712295",
      "arxivId": null,
      "url": "https://www.semanticscholar.org/paper/baf3d092bb968f2350487b6afc673f38d354f793",
      "venue": "",
      "journal": {
        "name": "",
        "volume": ""
      },
      "publicationTypes": null
    },
    {
      "paperId": "0ce49465495c6f5b8eca743f87645152cf72be89",
      "title": "Organizational Ethics and the Good Life",
      "authors": [
        {
          "name": "Edwin M. Hartman",
          "authorId": "144973867"
        }
      ],
      "year": 1996,
      "abstract": null,
      "citationCount": 197,
      "doi": null,
      "arxivId": null,
      "url": "https://www.semanticscholar.org/paper/0ce49465495c6f5b8eca743f87645152cf72be89",
      "venue": "",
      "journal": {
        "name": "",
        "volume": ""
      },
      "publicationTypes": null
    },
    {
      "paperId": "fef85a1b90ff6107160551007c1dd09f45d58839",
      "title": "Charles L. DeFanti Jr, The Wages of Expectation: A Biography of Edward Dahlberg (New York: New York University Press, 1978, $15.00 cloth, $6.95 paper). Pp. v, 272.",
      "authors": [
        {
          "name": "P. Melling",
          "authorId": "6629460"
        }
      ],
      "year": 1981,
      "abstract": null,
      "citationCount": 0,
      "doi": "10.1017/S0021875800005442",
      "arxivId": null,
      "url": "https://www.semanticscholar.org/paper/fef85a1b90ff6107160551007c1dd09f45d58839",
      "venue": "Journal of American Studies",
      "journal": {
        "name": "Journal of American Studies",
        "pages": "159 - 160",
        "volume": "15"
      },
      "publicationTypes": null
    },
    {
      "paperId": "76f547f926c22593d28918874f969e45fcaf3c7a",
      "title": "Effortless Action: Wu-wei As Conceptual Metaphor and Spiritual Ideal in Early China",
      "authors": [
        {
          "name": "E. Slingerland",
          "authorId": "2486302"
        }
      ],
      "year": 1998,
      "abstract": null,
      "citationCount": 302,
      "doi": "10.2307/25066756",
      "arxivId": null,
      "url": "https://www.semanticscholar.org/paper/76f547f926c22593d28918874f969e45fcaf3c7a",
      "venue": "",
      "journal": {
        "name": "",
        "volume": ""
      },
      "publicationTypes": null
    },
    {
      "paperId": "f047fa028431a5429edc228560fa98696d5256b3",
      "title": "Intersubjectivity in economics : agents and structures",
      "authors": [
        {
          "name": "E. Fullbrook",
          "authorId": "52047254"
        }
      ],
      "year": 2001,
      "abstract": null,
      "citationCount": 59,
      "doi": "10.4324/9780203116661",
      "arxivId": null,
      "url": "https://www.semanticscholar.org/paper/f047fa028431a5429edc228560fa98696d5256b3",
      "venue": "",
      "journal": {
        "name": "",
        "volume": ""
      },
      "publicationTypes": null
    },
    {
      "paperId": "3275ff2168a3e172583ee3ec9de87a8a0ae4ee31",
      "title": "Interwar Vienna : culture between tradition and modernity",
      "authors": [
        {
          "name": "D. Holmes",
          "authorId": "2149602741"
        },
        {
          "name": "Lisa S. Silverman",
          "authorId": "123681021"
        }
      ],
      "year": 2009,
      "abstract": null,
      "citationCount": 4,
      "doi": null,
      "arxivId": null,
      "url": "https://www.semanticscholar.org/paper/3275ff2168a3e172583ee3ec9de87a8a0ae4ee31",
      "venue": "",
      "journal": {
        "name": "",
        "volume": ""
      },
      "publicationTypes": null
    },
    {
      "paperId": "2efc77a8d70a4d26cdf75114c2f6c225786c5706",
      "title": "Critical Theory Since Plato",
      "authors": [
        {
          "name": "Hazard Adams",
          "authorId": "115215202"
        }
      ],
      "year": 1971,
      "abstract": null,
      "citationCount": 305,
      "doi": "10.2307/429626",
      "arxivId": null,
      "url": "https://www.semanticscholar.org/paper/2efc77a8d70a4d26cdf75114c2f6c225786c5706",
      "venue": "",
      "journal": {
        "name": "",
        "volume": ""
      },
      "publicationTypes": [
        "Review"
      ]
    }
  ],
  "count": 20,
  "errors": []
}
